malestrom/__init__.py
malestrom/interaction.py
malestrom-0.1.3.dist-info/METADATA
malestrom-0.1.3.dist-info/WHEEL
malestrom-0.1.3.dist-info/RECORD
