Metadata-Version: 2.4
Name: malestrom
Version: 0.1.3
Summary: interstellar object tidal stream simulator and tooling
Author-email: angusforrest <contact@angusforrest.com>
Requires-Python: >=3.10
Requires-Dist: annotated-types>=0.7.0
Requires-Dist: astropy>=7.1.0
Requires-Dist: galpy>=1.10.2
Requires-Dist: numpy>=1.26
Requires-Dist: pandas-stubs>=2.2.3.250527
Requires-Dist: pandas>=2.3.0
Requires-Dist: scipy>=1.16.0
